[
  {
    "username": "prueba",
    "email": "prueba@email.com",
    "password": "12345556",
    "image": "avatar-1678115605136.jpg",
    "id": 1
  },
  {
    "username": "prueba1",
    "email": "email1@email.com",
    "phone": "123123123",
    "password": "123123123",
    "image": "avatar-1678131546540.jpg",
    "id": 2
  },
  {
    "username": "prueba1",
    "email": "email1@email.com",
    "phone": "123123123",
    "password": "123123123",
    "image": "avatar-1678131562176.jpg",
    "id": 3
  }
]